{
  "required": true,
  "package": "me.mcblueparrot.client.mixin",
  "compatibilityLevel": "JAVA_8",
  "refmap": "mixins.solclient.refmap.json",
  "mixins": [
    "MixinEntity",
    "MixinEntityLivingBase",
    "MixinEntityPlayer",
    "MixinTileEntity",
    "MixinWorldInfo",
    "client.MixinActiveRenderInfo",
    "client.MixinChunkRenderContainer",
    "client.MixinEntityPlayerSP",
    "client.MixinEntityRenderer",
    "client.MixinGuiChat",
    "client.MixinGuiContainer",
    "client.MixinGuiIngame",
    "client.MixinGuiIngameMenu",
    "client.MixinGuiLanguage",
    "client.MixinGuiMainMenu",
    "client.MixinGuiNewChat",
    "client.MixinGuiScreen",
    "client.MixinGuiScreenResourcePacks",
    "client.MixinGuiSlot",
    "client.MixinItemRenderer",
    "client.MixinLocale",
    "client.MixinMinecraft",
    "client.MixinNetHandlerPlayClient",
    "client.MixinRender",
    "client.MixinRenderChunk",
    "client.MixinRenderEntityItem",
    "client.MixinRendererLivingEntity",
    "client.MixinRenderManager",
    "client.MixinScreenshotHelper",
    "client.MixinShaderGroup",
    "client.MixinSimpleReloadableResourceManager",
    "client.MixinTileEntityRenderDispatcher",
    "client.MixinWorldClient",
    "mod.MixinArabicNumeralsMod$MixinEnchantment",
    "mod.MixinArabicNumeralsMod$MixinInventoryEffectRenderer",
    "mod.MixinArabicNumeralsMod$MixinItemPotion",
    "mod.MixinBetterItemTooltipsMod$MixinGuiIngame",
    "mod.MixinChatHud$MixinGameSettings",
    "mod.MixinChatHud$MixinGuiChat",
    "mod.MixinChatHud$MixinGuiScreen",
    "mod.MixinChatHud$MixinGuiUtilRenderComponents",
    "mod.MixinHypixelAdditionsMod$MixinRenderPlayer",
    "mod.MixinNumeralPingMod$MixinGuiPlayerTabOverlay",
    "mod.MixinOld1_7AnimationsMod$MixinEntityRenderer",
    "mod.MixinOld1_7AnimationsMod$MixinItemRenderer",
    "mod.MixinOld1_7AnimationsMod$MixinLayerArmorBase",
    "mod.MixinSCReplayMod$MixinCameraEntity",
    "mod.MixinSCReplayMod$MixinEntityRenderer",
    "mod.MixinSCReplayMod$MixinGuiIngame",
    "mod.MixinSCReplayMod$MixinGuiReplayViewer",
    "mod.MixinSCReplayMod$MixinMCVer",
    "mod.MixinSCReplayMod$MixinMinecraft",
    "mod.MixinSCReplayMod$MixinReplayMod",
    "mod.MixinShowOwnTagMod$MixinRendererLivingEntity"
  ],
  "injectors": {
    "defaultRequire": 1
  }
}
